gatelogue_types/__about__.py
gatelogue_types/__init__.py
gatelogue_types-2.0.9.dist-info/METADATA
gatelogue_types-2.0.9.dist-info/WHEEL
gatelogue_types-2.0.9.dist-info/RECORD
