Metadata-Version: 2.4
Name: gatelogue-types
Version: 2.0.9
Summary: Types for loading and reading Gatelogue data
Project-URL: Documentation, https://mrt-map.github.io/gatelogue/docs
Project-URL: Issues, https://github.com/mrt-map/gatelogue/issues
Project-URL: Source, https://github.com/mrt-map/gatelogue
Project-URL: Changelog, https://github.com/MRT-Map/gatelogue/blob/main/CHANGELOG.md
Project-URL: Homepage, https://mrt-map.github.io/gatelogue
Author: MRT Mapping Services
Author-email: 7d <61975820+iiiii7d@users.noreply.github.com>
License-Expression: GPL-3.0-only
Keywords: gatelogue,minecart rapid transit,mrt
Classifier: Development Status :: 4 - Beta
Classifier: Intended Audience :: Developers
Classifier: License :: OSI Approved :: GNU General Public License v3 (GPLv3)
Classifier: Programming Language :: Python
Classifier: Programming Language :: Python :: 3.12
Classifier: Programming Language :: Python :: 3.13
Classifier: Programming Language :: Python :: Implementation :: CPython
Classifier: Topic :: Games/Entertainment
Classifier: Typing :: Typed
Requires-Python: >=3.12
Requires-Dist: msgspec~=0.19
